bolides/__init__.py
bolides/astro_utils.py
bolides/bdf.py
bolides/bolide.py
bolides/bolidelist.py
bolides/constants.py
bolides/crs.py
bolides/fov_utils.py
bolides/pipeline_utils.py
bolides/plotting.py
bolides/sdf.py
bolides/sources.py
bolides/utils.py
bolides/version.py
bolides/data/GLM_FOV_edges.nc
bolides/data/glm16_obs.csv
bolides/data/glm17_obs.csv
bolides/data/constellations/README.txt
bolides/data/constellations/anutan.csv
bolides/data/constellations/aztec.csv
bolides/data/constellations/belarusian.csv
bolides/data/constellations/boorong.csv
bolides/data/constellations/chinese.csv
bolides/data/constellations/chinese_contemporary.csv
bolides/data/constellations/chinese_medieval.csv
bolides/data/constellations/egyptian.csv
bolides/data/constellations/hawaiian_starlines.csv
bolides/data/constellations/indian.csv
bolides/data/constellations/inuit.csv
bolides/data/constellations/japanese_moon_stations.csv
bolides/data/constellations/korean.csv
bolides/data/constellations/lokono.csv
bolides/data/constellations/macedonian.csv
bolides/data/constellations/maori.csv
bolides/data/constellations/maya.csv
bolides/data/constellations/mongolian.csv
bolides/data/constellations/navajo.csv
bolides/data/constellations/norse.csv
bolides/data/constellations/northern_andes.csv
bolides/data/constellations/romanian.csv
bolides/data/constellations/russian_siberian.csv
bolides/data/constellations/sami.csv
bolides/data/constellations/sardinian.csv
bolides/data/constellations/tongan.csv
bolides/data/constellations/tukano.csv
bolides/data/constellations/tupi.csv
bolides/data/constellations/western.csv
bolides/data/constellations/western_SnT.csv
bolides/data/constellations/western_hlad.csv
bolides/data/constellations/western_rey.csv
bolides/data/gmn/100km.cpg
bolides/data/gmn/100km.dbf
bolides/data/gmn/100km.prj
bolides/data/gmn/100km.shp
bolides/data/gmn/100km.shx
bolides/data/gmn/25km.cpg
bolides/data/gmn/25km.dbf
bolides/data/gmn/25km.prj
bolides/data/gmn/25km.shp
bolides-0.6.0.dist-info/licenses/AUTHORS
bolides-0.6.0.dist-info/licenses/LICENSE
bolides-0.6.0.dist-info/METADATA
bolides-0.6.0.dist-info/WHEEL
bolides-0.6.0.dist-info/top_level.txt
bolides-0.6.0.dist-info/RECORD
