Metadata-Version: 2.4
Name: bolides
Version: 0.6.0
Summary: A package to analyze bolide data
Author-email: Anthony Ozerov <ozerov@berkeley.edu>, Jeffrey Smith <jsmith@seti.org>
Project-URL: Homepage, https://github.com/jcsmithhere/bolides
Project-URL: Bug Tracker, https://github.com/jcsmithhere/bolides/issues
Classifier: Development Status :: 5 - Production/Stable
Classifier: Programming Language :: Python :: 3
Classifier: License :: OSI Approved :: MIT License
Classifier: Operating System :: OS Independent
Requires-Python: >=3.7
License-File: LICENSE
License-File: AUTHORS
Requires-Dist: tqdm
Requires-Dist: numpy
Requires-Dist: pandas
Requires-Dist: ephem
Requires-Dist: geopandas
Requires-Dist: matplotlib
Requires-Dist: lightkurve
Requires-Dist: netCDF4
Requires-Dist: pyproj
Requires-Dist: astropy
Requires-Dist: simplekml
Requires-Dist: scikit-learn
Requires-Dist: watermark
Requires-Dist: beautifulsoup4
Requires-Dist: plotly
Provides-Extra: pipeline
Requires-Dist: ZODB; extra == "pipeline"
Requires-Dist: zc.zlibstorage; extra == "pipeline"
Provides-Extra: webapp
Requires-Dist: dash; extra == "webapp"
Requires-Dist: flask_caching; extra == "webapp"
Requires-Dist: gunicorn; extra == "webapp"
Dynamic: license-file
